README.txt
setup.py
collective/__init__.py
collective.categorizing.egg-info/PKG-INFO
collective.categorizing.egg-info/SOURCES.txt
collective.categorizing.egg-info/dependency_links.txt
collective.categorizing.egg-info/entry_points.txt
collective.categorizing.egg-info/namespace_packages.txt
collective.categorizing.egg-info/not-zip-safe
collective.categorizing.egg-info/paster_plugins.txt
collective.categorizing.egg-info/requires.txt
collective.categorizing.egg-info/top_level.txt
collective/categorizing/__init__.py
collective/categorizing/configure.zcml
collective/categorizing/exceptions.py
collective/categorizing/version.txt
collective/categorizing/adapter/__init__.py
collective/categorizing/adapter/category.py
collective/categorizing/adapter/configure.zcml
collective/categorizing/browser/__init__.py
collective/categorizing/browser/categories.pt
collective/categorizing/browser/category-nav-selection.pt
collective/categorizing/browser/category-nav.pt
collective/categorizing/browser/category.pt
collective/categorizing/browser/category.py
collective/categorizing/browser/categorycontainer.pt
collective/categorizing/browser/configure.zcml
collective/categorizing/content/__init__.py
collective/categorizing/content/category.py
collective/categorizing/content/categorycontainer.py
collective/categorizing/content/configure.zcml
collective/categorizing/interfaces/__init__.py
collective/categorizing/interfaces/adapter.py
collective/categorizing/interfaces/content.py
collective/categorizing/interfaces/viewlet_manager.py
collective/categorizing/locales/collective.categorizing.pot
collective/categorizing/locales/fr/LC_MESSAGES/collective.categorizing.po
collective/categorizing/locales/ja/LC_MESSAGES/collective.categorizing.po
collective/categorizing/portlets/__init__.py
collective/categorizing/portlets/categorizing.pt
collective/categorizing/portlets/categorizing.py
collective/categorizing/portlets/configure.zcml
collective/categorizing/profiles/default/catalog.xml
collective/categorizing/profiles/default/factorytool.xml
collective/categorizing/profiles/default/metadata.xml
collective/categorizing/profiles/default/portlets.xml
collective/categorizing/profiles/default/rolemap.xml
collective/categorizing/profiles/default/types.xml
collective/categorizing/profiles/default/viewlets.xml
collective/categorizing/profiles/default/types/Category.xml
collective/categorizing/profiles/default/types/CategoryContainer.xml
