Metadata-Version: 1.0
Name: collective.categorizing
Version: 0.2.3
Summary: collective.categorizing aims to add hierarchical categorizing to Plone with Category content type.
Home-page: http://pypi.python.org/pypi/collective.categorizing
Author: Taito Horiuchi
Author-email: taito.horiuchi@gmail.com
License: GPL
Platform: UNKNOWN
Classifier: Framework :: Plone
Classifier: Programming Language :: Python
Classifier: Topic :: Software Development :: Libraries :: Python Modules
